{
  "titleSlug": "running-total-for-different-genders",
  "acRate": 86.29298367488711,
  "content": null,
  "difficulty": "Medium",
  "freqBar": null,
  "frontendQuestionId": "1308",
  "hasSolution": false,
  "hasVideoSolution": false,
  "hints": [],
  "isFavor": false,
  "paidOnly": true,
  "similarQuestionList": [
    {
      "difficulty": "Medium",
      "titleSlug": "last-person-to-fit-in-the-bus",
      "title": "Last Person to Fit in the Bus",
      "translatedTitle": null,
      "isPaidOnly": false
    }
  ],
  "status": null,
  "title": "Running Total for Different Genders",
  "topicTags": [
    {
      "name": "Database",
      "id": "VG9waWNUYWdOb2RlOjYxMDQz",
      "slug": "database"
    }
  ]
}