{
  "titleSlug": "diagonal-traverse",
  "acRate": 59.91414499451264,
  "content": "<p>Given an <code>m x n</code> matrix <code>mat</code>, return <em>an array of all the elements of the array in a diagonal order</em>.</p>\n\n<p>&nbsp;</p>\n<p><strong class=\"example\">Example 1:</strong></p>\n<img alt=\"\" src=\"https://assets.leetcode.com/uploads/2021/04/10/diag1-grid.jpg\" style=\"width: 334px; height: 334px;\" />\n<pre>\n<strong>Input:</strong> mat = [[1,2,3],[4,5,6],[7,8,9]]\n<strong>Output:</strong> [1,2,4,7,5,3,6,8,9]\n</pre>\n\n<p><strong class=\"example\">Example 2:</strong></p>\n\n<pre>\n<strong>Input:</strong> mat = [[1,2],[3,4]]\n<strong>Output:</strong> [1,2,3,4]\n</pre>\n\n<p>&nbsp;</p>\n<p><strong>Constraints:</strong></p>\n\n<ul>\n\t<li><code>m == mat.length</code></li>\n\t<li><code>n == mat[i].length</code></li>\n\t<li><code>1 &lt;= m, n &lt;= 10<sup>4</sup></code></li>\n\t<li><code>1 &lt;= m * n &lt;= 10<sup>4</sup></code></li>\n\t<li><code>-10<sup>5</sup> &lt;= mat[i][j] &lt;= 10<sup>5</sup></code></li>\n</ul>\n",
  "difficulty": "Medium",
  "freqBar": null,
  "frontendQuestionId": "498",
  "hasSolution": true,
  "hasVideoSolution": false,
  "hints": [],
  "isFavor": false,
  "paidOnly": false,
  "similarQuestionList": [
    {
      "difficulty": "Medium",
      "titleSlug": "decode-the-slanted-ciphertext",
      "title": "Decode the Slanted Ciphertext",
      "translatedTitle": null,
      "isPaidOnly": false
    }
  ],
  "status": null,
  "title": "Diagonal Traverse",
  "topicTags": [
    {
      "name": "Array",
      "id": "VG9waWNUYWdOb2RlOjU=",
      "slug": "array"
    },
    {
      "name": "Matrix",
      "id": "VG9waWNUYWdOb2RlOjYxMDUz",
      "slug": "matrix"
    },
    {
      "name": "Simulation",
      "id": "VG9waWNUYWdOb2RlOjYxMDU1",
      "slug": "simulation"
    }
  ]
}